FHColors/__init__.py
FHColors/colors.py
FHColors-1.0.1.dist-info/LICENCE
FHColors-1.0.1.dist-info/METADATA
FHColors-1.0.1.dist-info/WHEEL
FHColors-1.0.1.dist-info/top_level.txt
FHColors-1.0.1.dist-info/RECORD
