Metadata-Version: 2.1
Name: FHColors
Version: 1.0.1
Summary: A Package containing the corporate design colers of Fraunhofer Gesellschaft
Home-page: UNKNOWN
Author: Jan Paschen
Author-email: jan@ej-paschen.de
License: UNKNOWN
Keywords: python,first package
Platform: UNKNOWN
Classifier: Programming Language :: Python :: 3
Classifier: License :: OSI Approved :: MIT License
Classifier: Operating System :: OS Independent
Requires-Python: >=3.6
Requires-Dist: matplotlib
Requires-Dist: numpy
